setup.py
ansible_universe.egg-info/PKG-INFO
ansible_universe.egg-info/SOURCES.txt
ansible_universe.egg-info/dependency_links.txt
ansible_universe.egg-info/entry_points.txt
ansible_universe.egg-info/requires.txt
ansible_universe.egg-info/top_level.txt
universe/__init__.py
universe/__main__.py
universe/copy_has_owner.py
universe/manifest_has_author.py
universe/manifest_has_license.py
universe/manifest_has_platforms.py
universe/manifest_has_version.py
universe/subdir_is_defined.py
universe/syntax_is_ok.py
universe/task_has_name.py
universe/task_has_no_remote_user.py
universe/template_has_owner.py
universe/variable_is_documented.py
universe/variable_is_prefixed.py