Metadata-Version: 1.0
Name: ansible-universe
Version: 1.11.12
Summary: Ansible role build tool
Home-page: https://github.com/fclaerho/ansible-universe
Author: florent claerhout
Author-email: code@fclaerhout.fr
License: MIT
Platform: UNKNOWN
